.travis.yml
MANIFEST.in
Makefile
README.rst
setup.py
docs/CHANGELOG.rst
docs/CREDITS.txt
docs/LICENSE.rst
docs/api.rst
docs/conf.py
docs/glossary.rst
docs/index.rst
docs/_static/.gitkeep
rg/__init__.py
rg.infocard.egg-info/PKG-INFO
rg.infocard.egg-info/SOURCES.txt
rg.infocard.egg-info/dependency_links.txt
rg.infocard.egg-info/entry_points.txt
rg.infocard.egg-info/namespace_packages.txt
rg.infocard.egg-info/not-zip-safe
rg.infocard.egg-info/requires.txt
rg.infocard.egg-info/top_level.txt
rg/infocard/__init__.py
rg/infocard/configure.zcml
rg/infocard/i18n.sh
rg/infocard/interfaces.py
rg/infocard/testing.py
rg/infocard/browser/__init__.py
rg/infocard/browser/configure.zcml
rg/infocard/browser/infocard.py
rg/infocard/browser/infocard_view.py
rg/infocard/browser/infocardcontainer.py
rg/infocard/browser/infocardcontainer_search.py
rg/infocard/browser/overrides/.gitkeep
rg/infocard/browser/static/.gitkeep
rg/infocard/browser/static/css/infocard.css
rg/infocard/browser/static/css/infocardcontainer_search.css
rg/infocard/browser/static/css/rg.infocard.edit.css
rg/infocard/browser/static/images/infocard.png
rg/infocard/browser/static/images/infocardcontainer.png
rg/infocard/browser/static/scripts/infocardcontainer_search.js
rg/infocard/browser/static/scripts/rg.infocard.edit.js
rg/infocard/browser/templates/cell_rich_text_widget_input.pt
rg/infocard/browser/templates/infocard_view.pt
rg/infocard/browser/templates/infocardcontainer_search.pt
rg/infocard/browser/templates/rg.infocard.layout.pt
rg/infocard/events/__init__.py
rg/infocard/events/configure.zcml
rg/infocard/events/infocard.py
rg/infocard/fields/__init__.py
rg/infocard/fields/infocard_complex_field.py
rg/infocard/locales/rg.infocard-manual.pot
rg/infocard/locales/rg.infocard.pot
rg/infocard/locales/en/LC_MESSAGES/rg.infocard.po
rg/infocard/locales/it/LC_MESSAGES/rg.infocard.po
rg/infocard/models/__init__.py
rg/infocard/models/base.py
rg/infocard/models/infocard.py
rg/infocard/models/infocard.xml
rg/infocard/models/infocardcontainer.py
rg/infocard/models/infocardcontainer.xml
rg/infocard/portlets/__init__.py
rg/infocard/portlets/configure.zcml
rg/infocard/portlets/search.pt
rg/infocard/portlets/search.py
rg/infocard/profiles/default/browserlayer.xml
rg/infocard/profiles/default/metadata.xml
