Metadata-Version: 1.1
Name: rg.infocard
Version: 0.9.4
Summary: rg.infocard
Home-page: http://pypi.python.org/pypi/rg.infocard
Author: RedTurtle Technology
Author-email: sviluppoplone@redturtle.it
License: GPL
Keywords: Plone
Platform: UNKNOWN
Classifier: Framework :: Plone
Classifier: Programming Language :: Python
Classifier: License :: OSI Approved :: GNU General Public License (GPL)
